src/__init__.py
src/mcp_tools/__init__.py
src/mcp_tools/dusting_tool.py
src/mcp_tools/poisoning_tool.py
src/utils/__init__.py
src/utils/constants.py
src/utils/dust_analyzer.py
src/utils/poisoning_analyzer.py
mseep_solsecurity_mcp-0.1.2.dist-info/METADATA
mseep_solsecurity_mcp-0.1.2.dist-info/WHEEL
mseep_solsecurity_mcp-0.1.2.dist-info/entry_points.txt
mseep_solsecurity_mcp-0.1.2.dist-info/RECORD
