Metadata-Version: 2.4
Name: mseep-solsecurity-mcp
Version: 0.1.2
Summary: Solana wallet security analysis tool
Author-email: mseep <support@skydeck.ai>
Requires-Python: >=3.11
Requires-Dist: httpx>=0.28.1
Requires-Dist: mcp[cli]>=1.9.0
Requires-Dist: python-dotenv
